MANIFEST.in
README
ez_setup.py
setup.cfg
setup.py
setuptools-0.6c9-py2.5.egg
bin/pysqueezecenter
docs/.gitignore
docs/Makefile
docs/build/.buildinfo
docs/build/.doctrees/environment.pickle
docs/build/.doctrees/index.doctree
docs/build/.doctrees/test.doctree
docs/build/doctrees/cli.doctree
docs/build/doctrees/environment.pickle
docs/build/doctrees/index.doctree
docs/build/doctrees/player.doctree
docs/build/doctrees/server.doctree
docs/build/doctrees/utils.doctree
docs/build/html/.buildinfo
docs/build/html/cli.html
docs/build/html/genindex.html
docs/build/html/index.html
docs/build/html/objects.inv
docs/build/html/player.html
docs/build/html/search.html
docs/build/html/searchindex.js
docs/build/html/server.html
docs/build/html/utils.html
docs/build/html/.doctrees/environment.pickle
docs/build/html/.doctrees/index.doctree
docs/build/html/.doctrees/player.doctree
docs/build/html/.doctrees/server.doctree
docs/build/html/_sources/cli.txt
docs/build/html/_sources/index.txt
docs/build/html/_sources/player.txt
docs/build/html/_sources/server.txt
docs/build/html/_sources/utils.txt
docs/build/html/_static/basic.css
docs/build/html/_static/default.css
docs/build/html/_static/doctools.js
docs/build/html/_static/file.png
docs/build/html/_static/jquery.js
docs/build/html/_static/minus.png
docs/build/html/_static/plus.png
docs/build/html/_static/pygments.css
docs/build/html/_static/searchtools.js
docs/build/html/_static/sidebar.js
docs/build/html/_static/underscore.js
docs/build/html/doctrees/environment.pickle
docs/build/html/doctrees/index.doctree
docs/build/html/doctrees/player.doctree
docs/build/html/doctrees/server.doctree
docs/source/cli.rst
docs/source/conf.py
docs/source/index.rst
docs/source/player.rst
docs/source/server.rst
docs/source/utils.rst
pysqueezecenter/__init__.py
pysqueezecenter/__init__.pyc
pysqueezecenter/player.py
pysqueezecenter/player.pyc
pysqueezecenter/server.py
pysqueezecenter/server.pyc
pysqueezecenter/tests.py
pysqueezecenter/utils.py
pysqueezecenter.egg-info/PKG-INFO
pysqueezecenter.egg-info/SOURCES.txt
pysqueezecenter.egg-info/dependency_links.txt
pysqueezecenter.egg-info/top_level.txt
