Metadata-Version: 1.0
Name: pysqueezecenter
Version: 0.95
Summary: PySqueezeCenter
Home-page: http://www.louisking.co.uk
Author: Louis King
Author-email: jinglemansweep@gmail.com
License: UNKNOWN
Platform: UNKNOWN
Classifier: Development Status :: 2 - Pre-Alpha
Classifier: Environment :: Console
Classifier: Intended Audience :: Developers
Classifier: Intended Audience :: End Users/Desktop
Classifier: License :: OSI Approved :: GNU General Public License (GPL)
Classifier: Natural Language :: English
Classifier: Operating System :: POSIX :: Linux
Classifier: Programming Language :: Python :: 2.5
